Workbook
Name client_name: 'Cover'!$B$4
Name dashboard_kpis: 'Dashboard'!$A$4:$H$5
Name data_block: 'Data'!$A$2:$D$4
Name headline_kpi: 'Summary'!$B$9
Name inputs_block: 'Inputs'!$A$4:$C$7
Name model_body: 'Model'!$A$4:$G$6
Name period: 'Cover'!$B$5
Name report_subtitle: 'Cover'!$A$2
Name report_title: 'Cover'!$A$1
Name scenario_block: 'Scenarios'!$A$5:$D$8
Name q_total: Model!$F$7

Sheet Cover
A1: FY2025 Revenue Performance Review
A2: Quarterly revenue model and executive summary
A4: Prepared for | B4: BrandDocs Corp (synthetic demo) | D4: FY net revenue | E4: Net margin | F4: Brand audit | G4: Scope
A5: Reporting period | B5: FY2025 (Q1-Q4) | D5: =Summary!B4 | E5: =Summary!B8 | F5: Deep QA | G5: 3 formats
A6: Generated on | B6: 2026-01-15
D11: Legend
D12: Inputs | E12: Blue fill = editable assumptions you fill in
D13: Formulas | E13: Navy text = model formulas (do not overwrite)

Sheet Inputs
A1: Model Inputs
A3: Driver | B3: Value | C3: Unit
A4: Units sold | B4: 29070 | C4: ea
A5: Unit price | B5: 50 | C5: USD
A6: Discount rate | B6: 0.12 | C6: pct
A7: Tax rate | B7: 0.22 | C7: pct

Sheet Model
A1: Revenue Model
A3: Line item | B3: Q1 | C3: Q2 | D3: Q3 | E3: Q4 | F3: FY Total | G3: % of FY
A4: Gross revenue | B4: 320000 | C4: 351000 | D4: 372500 | E4: 410000 | F4: =SUM(B4:E4) | G4: =IF($F$7=0,0,F4/$F$7)
A5: Discounts | B5: -38400 | C5: -42120 | D5: -44700 | E5: -49200 | F5: =SUM(B5:E5) | G5: =IF($F$7=0,0,F5/$F$7)
A6: Returns | B6: -9600 | C6: -10530 | D6: -11175 | E6: -12300 | F6: =SUM(B6:E6) | G6: =IF($F$7=0,0,F6/$F$7)
A7: Net revenue | B7: =SUM(B4:B6) | C7: =SUM(C4:C6) | D7: =SUM(D4:D6) | E7: =SUM(E4:E6) | F7: =SUM(B7:E7) | G7: =IF($F$7=0,0,F7/$F$7)
A8: Total | F8: =SUBTOTAL(109,F4:F7)
A10: Subtotal (visible) | F10: =SUBTOTAL(9,F4:F6) | G10: =SUM(BrandDocsDataTbl[FY Total])

Sheet Summary
A1: Executive Summary
A3: Metric | B3: Value
A4: FY net revenue | B4: =Model!F7
A5: Units sold (input) | B5: =Inputs!B4
A6: Unit price (input) | B6: =Inputs!B5
A7: Implied gross | B7: =Inputs!B4*Inputs!B5
A8: Net margin | B8: =IF(B7=0,0,B4/B7)
A9: Headline KPI | B9: 85% net margin on $1.45M gross

Sheet Dashboard
A1: Executive Dashboard
A2: Formula-backed snapshot generated from the model, inputs, and summary tabs
A4: FY net revenue | C4: Net margin | E4: Input units | G4: Scenario
A5: =Summary!B4 | C5: =Summary!B8 | E5: =Summary!B5 | G5: =Scenarios!B3
A7: Quarter | B7: Net revenue | C7: Growth
A8: Q1 | B8: =Model!B7 | C8: -
A9: Q2 | B9: =Model!C7 | C9: =IF(B8=0,0,B9/B8-1)
A10: Q3 | B10: =Model!D7 | C10: =IF(B9=0,0,B10/B9-1)
A11: Q4 | B11: =Model!E7 | C11: =IF(B10=0,0,B11/B10-1)
A14: KPI trends
A15: KPI | B15: Q1 | C15: Q2 | D15: Q3 | E15: Q4 | F15: Trend | G15: QoQ / delta
A16: Net revenue | B16: 272000 | C16: 298350 | D16: 316625 | E16: 348500 | G16: =IF(B11=0,0,B11/B8-1)
A17: Bookings | B17: 240000 | C17: 281000 | D17: 305000 | E17: 366000 | G17: =ROUND((Summary!B8-0.85)*10000,0)
A18: Active seats | B18: 1180 | C18: 1240 | D18: 1305 | E18: 1402

Sheet Scenarios
A1: Scenario Controls
A3: Selected scenario | B3: Base
A5: Scenario | B5: Revenue multiplier | C5: Margin delta | D5: Narrative
A6: Base | B6: 1 | C6: 0 | D6: Plan case
A7: Upside | B7: 1.12 | C7: 0.025 | D7: Faster adoption
A8: Downside | B8: 0.91 | C8: -0.035 | D8: Cost pressure
A10: Scenario revenue | B10: =Summary!B4*INDEX(B6:B8,MATCH($B$3,A6:A8,0))
A11: Scenario margin | B11: =Summary!B8+INDEX(C6:C8,MATCH($B$3,A6:A8,0))

Sheet Data
A1: Date | B1: Region | C1: Product | D1: Amount
A2: 2025-10-01 | B2: North | C2: Widget | D2: 12500
A3: 2025-10-02 | B3: South | C3: Gadget | D3: 9800
A4: 2025-10-03 | B4: East | C4: Widget | D4: 14200
C5: Total | D5: =SUM(D2:D4)
